[{"RouteNo":"005","RouteName":"ROBSON\/DOWNTOWN                ","Direction":"EAST","RouteMap":{"Href":"http:\/\/nb.translink.ca\/geodata\/005.kmz"},"Schedules":[{"Pattern":"EB1","Destination":"DOWNTOWN","ExpectedLeaveTime":"6:55pm 2017-08-22","ExpectedCountdown":0,"ScheduleStatus":"-","CancelledTrip":false,"CancelledStop":false,"AddedTrip":false,"AddedStop":false,"LastUpdate":"05:41:03 pm"},{"Pattern":"EB1","Destination":"DOWNTOWN","ExpectedLeaveTime":"6:55pm 2017-08-22","ExpectedCountdown":0,"ScheduleStatus":"+","CancelledTrip":false,"CancelledStop":false,"AddedTrip":false,"AddedStop":false,"LastUpdate":"06:55:08 pm"},{"Pattern":"EB1","Destination":"DOWNTOWN","ExpectedLeaveTime":"7:06pm 2017-08-22","ExpectedCountdown":11,"ScheduleStatus":" ","CancelledTrip":false,"CancelledStop":false,"AddedTrip":false,"AddedStop":false,"LastUpdate":"05:56:00 pm"},{"Pattern":"EB1","Destination":"DOWNTOWN","ExpectedLeaveTime":"7:15pm 2017-08-22","ExpectedCountdown":20,"ScheduleStatus":"-","CancelledTrip":false,"CancelledStop":false,"AddedTrip":false,"AddedStop":false,"LastUpdate":"06:03:13 pm"},{"Pattern":"EB1","Destination":"DOWNTOWN","ExpectedLeaveTime":"7:21pm 2017-08-22","ExpectedCountdown":26,"ScheduleStatus":"*","CancelledTrip":false,"CancelledStop":false,"AddedTrip":false,"AddedStop":false,"LastUpdate":"06:11:06 pm"},{"Pattern":"EB1","Destination":"DOWNTOWN","ExpectedLeaveTime":"7:28pm 2017-08-22","ExpectedCountdown":33,"ScheduleStatus":"*","CancelledTrip":false,"CancelledStop":false,"AddedTrip":false,"AddedStop":false,"LastUpdate":"06:18:00 pm"}]}]