[{"RouteNo":"002","RouteName":"MACDONALD\/DOWNTOWN ","Direction":"EAST","RouteMap":{"Href":"http:\/\/nb.translink.ca\/geodata\/002.kmz"},"Schedules":[{"Pattern":"EB1","Destination":"DOWNTOWN","ExpectedLeaveTime":"6:09pm 2017-08-22","ExpectedCountdown":11,"ScheduleStatus":"-","CancelledTrip":false,"CancelledStop":false,"AddedTrip":false,"AddedStop":false,"LastUpdate":"05:57:55 pm"},{"Pattern":"EB2","Destination":"DOWNTOWN","ExpectedLeaveTime":"6:13pm 2017-08-22","ExpectedCountdown":15,"ScheduleStatus":" ","CancelledTrip":false,"CancelledStop":false,"AddedTrip":false,"AddedStop":false,"LastUpdate":"04:51:01 pm"},{"Pattern":"EB2","Destination":"DOWNTOWN","ExpectedLeaveTime":"6:13pm 2017-08-22","ExpectedCountdown":15,"ScheduleStatus":"-","CancelledTrip":false,"CancelledStop":false,"AddedTrip":false,"AddedStop":false,"LastUpdate":"05:57:54 pm"},{"Pattern":"EB1","Destination":"DOWNTOWN","ExpectedLeaveTime":"6:22pm 2017-08-22","ExpectedCountdown":24,"ScheduleStatus":"-","CancelledTrip":false,"CancelledStop":false,"AddedTrip":false,"AddedStop":false,"LastUpdate":"04:49:09 pm"},{"Pattern":"EB1","Destination":"DOWNTOWN","ExpectedLeaveTime":"6:22pm 2017-08-22","ExpectedCountdown":24,"ScheduleStatus":"-","CancelledTrip":false,"CancelledStop":false,"AddedTrip":false,"AddedStop":false,"LastUpdate":"04:35:11 pm"},{"Pattern":"EB2","Destination":"DOWNTOWN","ExpectedLeaveTime":"6:27pm 2017-08-22","ExpectedCountdown":29,"ScheduleStatus":" ","CancelledTrip":false,"CancelledStop":false,"AddedTrip":false,"AddedStop":false,"LastUpdate":"05:05:08 pm"}]},{"RouteNo":"044","RouteName":"UBC\/DOWNTOWN                    ","Direction":"EAST","RouteMap":{"Href":"http:\/\/nb.translink.ca\/geodata\/044.kmz"},"Schedules":[{"Pattern":"EB1","Destination":"DOWNTOWN","ExpectedLeaveTime":"6:11pm 2017-08-22","ExpectedCountdown":13,"ScheduleStatus":"+","CancelledTrip":false,"CancelledStop":false,"AddedTrip":false,"AddedStop":false,"LastUpdate":"05:55:49 pm"},{"Pattern":"EB1","Destination":"DOWNTOWN","ExpectedLeaveTime":"6:40pm 2017-08-22","ExpectedCountdown":42,"ScheduleStatus":"-","CancelledTrip":false,"CancelledStop":false,"AddedTrip":false,"AddedStop":false,"LastUpdate":"04:58:05 pm"},{"Pattern":"EB1","Destination":"DOWNTOWN","ExpectedLeaveTime":"6:56pm 2017-08-22","ExpectedCountdown":58,"ScheduleStatus":"-","CancelledTrip":false,"CancelledStop":false,"AddedTrip":false,"AddedStop":false,"LastUpdate":"05:13:04 pm"},{"Pattern":"EB1","Destination":"DOWNTOWN","ExpectedLeaveTime":"7:04pm 2017-08-22","ExpectedCountdown":66,"ScheduleStatus":"-","CancelledTrip":false,"CancelledStop":false,"AddedTrip":false,"AddedStop":false,"LastUpdate":"05:28:11 pm"},{"Pattern":"EB1","Destination":"DOWNTOWN","ExpectedLeaveTime":"7:12pm 2017-08-22","ExpectedCountdown":74,"ScheduleStatus":" ","CancelledTrip":false,"CancelledStop":false,"AddedTrip":false,"AddedStop":false,"LastUpdate":"05:43:07 pm"},{"Pattern":"EB1","Destination":"DOWNTOWN","ExpectedLeaveTime":"7:27pm 2017-08-22","ExpectedCountdown":89,"ScheduleStatus":" ","CancelledTrip":false,"CancelledStop":false,"AddedTrip":false,"AddedStop":false,"LastUpdate":"05:58:03 pm"}]}]