[{"RouteNo":"004","RouteName":"POWELL\/DOWNTOWN\/UBC","Direction":"EAST","RouteMap":{"Href":"http:\/\/nb.translink.ca\/geodata\/004.kmz"},"Schedules":[{"Pattern":"EB1","Destination":"POWELL","ExpectedLeaveTime":"5:39pm 2017-08-21","ExpectedCountdown":8,"ScheduleStatus":"-","CancelledTrip":false,"CancelledStop":false,"AddedTrip":false,"AddedStop":false,"LastUpdate":"05:29:53 pm"},{"Pattern":"EB1","Destination":"POWELL","ExpectedLeaveTime":"5:57pm 2017-08-21","ExpectedCountdown":26,"ScheduleStatus":" ","CancelledTrip":false,"CancelledStop":false,"AddedTrip":false,"AddedStop":false,"LastUpdate":"04:39:01 pm"},{"Pattern":"EB1","Destination":"POWELL","ExpectedLeaveTime":"6:17pm 2017-08-21","ExpectedCountdown":46,"ScheduleStatus":"*","CancelledTrip":false,"CancelledStop":false,"AddedTrip":false,"AddedStop":false,"LastUpdate":"04:59:01 pm"},{"Pattern":"EB1","Destination":"POWELL","ExpectedLeaveTime":"6:37pm 2017-08-21","ExpectedCountdown":66,"ScheduleStatus":" ","CancelledTrip":false,"CancelledStop":false,"AddedTrip":false,"AddedStop":false,"LastUpdate":"05:19:07 pm"},{"Pattern":"EB1","Destination":"POWELL","ExpectedLeaveTime":"6:57pm 2017-08-21","ExpectedCountdown":86,"ScheduleStatus":"*","CancelledTrip":false,"CancelledStop":false,"AddedTrip":false,"AddedStop":false,"LastUpdate":"09:00:05 pm"},{"Pattern":"EB1","Destination":"POWELL","ExpectedLeaveTime":"7:17pm 2017-08-21","ExpectedCountdown":106,"ScheduleStatus":"*","CancelledTrip":false,"CancelledStop":false,"AddedTrip":false,"AddedStop":false,"LastUpdate":"09:00:05 pm"}]},{"RouteNo":"007","RouteName":"NANAIMO STN\/DUNBAR             ","Direction":"EAST","RouteMap":{"Href":"http:\/\/nb.translink.ca\/geodata\/007.kmz"},"Schedules":[{"Pattern":"EB1","Destination":"NANAIMO STN","ExpectedLeaveTime":"5:47pm 2017-08-21","ExpectedCountdown":16,"ScheduleStatus":" ","CancelledTrip":false,"CancelledStop":false,"AddedTrip":false,"AddedStop":false,"LastUpdate":"04:28:09 pm"},{"Pattern":"EB1","Destination":"NANAIMO STN","ExpectedLeaveTime":"6:07pm 2017-08-21","ExpectedCountdown":36,"ScheduleStatus":"*","CancelledTrip":false,"CancelledStop":false,"AddedTrip":false,"AddedStop":false,"LastUpdate":"04:48:05 pm"},{"Pattern":"EB1","Destination":"NANAIMO STN","ExpectedLeaveTime":"6:27pm 2017-08-21","ExpectedCountdown":56,"ScheduleStatus":" ","CancelledTrip":false,"CancelledStop":false,"AddedTrip":false,"AddedStop":false,"LastUpdate":"05:08:05 pm"},{"Pattern":"EB1","Destination":"NANAIMO STN","ExpectedLeaveTime":"6:47pm 2017-08-21","ExpectedCountdown":76,"ScheduleStatus":" ","CancelledTrip":false,"CancelledStop":false,"AddedTrip":false,"AddedStop":false,"LastUpdate":"05:28:05 pm"},{"Pattern":"EB1","Destination":"NANAIMO STN","ExpectedLeaveTime":"7:07pm 2017-08-21","ExpectedCountdown":96,"ScheduleStatus":"*","CancelledTrip":false,"CancelledStop":false,"AddedTrip":false,"AddedStop":false,"LastUpdate":"09:00:05 pm"},{"Pattern":"EB1","Destination":"NANAIMO STN","ExpectedLeaveTime":"7:27pm 2017-08-21","ExpectedCountdown":116,"ScheduleStatus":"*","CancelledTrip":false,"CancelledStop":false,"AddedTrip":false,"AddedStop":false,"LastUpdate":"09:00:05 pm"}]},{"RouteNo":"044","RouteName":"UBC\/DOWNTOWN                    ","Direction":"EAST","RouteMap":{"Href":"http:\/\/nb.translink.ca\/geodata\/044.kmz"},"Schedules":[{"Pattern":"EB1","Destination":"DOWNTOWN","ExpectedLeaveTime":"5:52pm 2017-08-21","ExpectedCountdown":21,"ScheduleStatus":" ","CancelledTrip":false,"CancelledStop":false,"AddedTrip":false,"AddedStop":false,"LastUpdate":"04:28:00 pm"},{"Pattern":"EB1","Destination":"DOWNTOWN","ExpectedLeaveTime":"6:11pm 2017-08-21","ExpectedCountdown":40,"ScheduleStatus":"-","CancelledTrip":false,"CancelledStop":false,"AddedTrip":false,"AddedStop":false,"LastUpdate":"04:43:01 pm"},{"Pattern":"EB1","Destination":"DOWNTOWN","ExpectedLeaveTime":"6:34pm 2017-08-21","ExpectedCountdown":63,"ScheduleStatus":" ","CancelledTrip":false,"CancelledStop":false,"AddedTrip":false,"AddedStop":false,"LastUpdate":"05:13:00 pm"},{"Pattern":"EB1","Destination":"DOWNTOWN","ExpectedLeaveTime":"6:35pm 2017-08-21","ExpectedCountdown":64,"ScheduleStatus":"-","CancelledTrip":false,"CancelledStop":false,"AddedTrip":false,"AddedStop":false,"LastUpdate":"04:58:06 pm"},{"Pattern":"EB1","Destination":"DOWNTOWN","ExpectedLeaveTime":"6:49pm 2017-08-21","ExpectedCountdown":78,"ScheduleStatus":" ","CancelledTrip":false,"CancelledStop":false,"AddedTrip":false,"AddedStop":false,"LastUpdate":"05:28:10 pm"},{"Pattern":"EB1","Destination":"DOWNTOWN","ExpectedLeaveTime":"7:02pm 2017-08-21","ExpectedCountdown":91,"ScheduleStatus":"*","CancelledTrip":false,"CancelledStop":false,"AddedTrip":false,"AddedStop":false,"LastUpdate":"09:00:05 pm"}]},{"RouteNo":"084","RouteName":"UBC\/VCC STATION","Direction":"EAST","RouteMap":{"Href":"http:\/\/nb.translink.ca\/geodata\/084.kmz"},"Schedules":[{"Pattern":"EB1","Destination":"VCC-CLARK STN","ExpectedLeaveTime":"5:33pm 2017-08-21","ExpectedCountdown":2,"ScheduleStatus":" ","CancelledTrip":false,"CancelledStop":false,"AddedTrip":false,"AddedStop":false,"LastUpdate":"04:18:07 pm"},{"Pattern":"EB1","Destination":"VCC-CLARK STN","ExpectedLeaveTime":"5:41pm 2017-08-21","ExpectedCountdown":10,"ScheduleStatus":" ","CancelledTrip":false,"CancelledStop":false,"AddedTrip":false,"AddedStop":false,"LastUpdate":"04:26:04 pm"},{"Pattern":"EB1","Destination":"VCC-CLARK STN","ExpectedLeaveTime":"5:51pm 2017-08-21","ExpectedCountdown":20,"ScheduleStatus":"-","CancelledTrip":false,"CancelledStop":false,"AddedTrip":false,"AddedStop":false,"LastUpdate":"04:34:01 pm"},{"Pattern":"EB1","Destination":"VCC-CLARK STN","ExpectedLeaveTime":"5:57pm 2017-08-21","ExpectedCountdown":26,"ScheduleStatus":"*","CancelledTrip":false,"CancelledStop":false,"AddedTrip":false,"AddedStop":false,"LastUpdate":"04:42:06 pm"},{"Pattern":"EB1","Destination":"VCC-CLARK STN","ExpectedLeaveTime":"6:05pm 2017-08-21","ExpectedCountdown":34,"ScheduleStatus":"*","CancelledTrip":false,"CancelledStop":false,"AddedTrip":false,"AddedStop":false,"LastUpdate":"04:50:07 pm"},{"Pattern":"EB1","Destination":"VCC-CLARK STN","ExpectedLeaveTime":"6:13pm 2017-08-21","ExpectedCountdown":42,"ScheduleStatus":" ","CancelledTrip":false,"CancelledStop":false,"AddedTrip":false,"AddedStop":false,"LastUpdate":"04:58:12 pm"}]}]