[{"RouteNo":"005","RouteName":"ROBSON\/DOWNTOWN                ","Direction":"EAST","RouteMap":{"Href":"http:\/\/nb.translink.ca\/geodata\/005.kmz"},"Schedules":[{"Pattern":"EB1","Destination":"DOWNTOWN","ExpectedLeaveTime":"3:55pm","ExpectedCountdown":-1,"ScheduleStatus":" ","CancelledTrip":false,"CancelledStop":false,"AddedTrip":false,"AddedStop":false,"LastUpdate":"02:54:04 pm"},{"Pattern":"EB1","Destination":"DOWNTOWN","ExpectedLeaveTime":"4:01pm","ExpectedCountdown":5,"ScheduleStatus":"*","CancelledTrip":false,"CancelledStop":false,"AddedTrip":false,"AddedStop":false,"LastUpdate":"03:00:01 pm"},{"Pattern":"EB1","Destination":"DOWNTOWN","ExpectedLeaveTime":"4:07pm","ExpectedCountdown":11,"ScheduleStatus":"*","CancelledTrip":false,"CancelledStop":false,"AddedTrip":false,"AddedStop":false,"LastUpdate":"03:06:06 pm"},{"Pattern":"EB1","Destination":"DOWNTOWN","ExpectedLeaveTime":"4:13pm","ExpectedCountdown":17,"ScheduleStatus":"*","CancelledTrip":false,"CancelledStop":false,"AddedTrip":false,"AddedStop":false,"LastUpdate":"03:12:08 pm"},{"Pattern":"EB1","Destination":"DOWNTOWN","ExpectedLeaveTime":"4:19pm","ExpectedCountdown":23,"ScheduleStatus":"*","CancelledTrip":false,"CancelledStop":false,"AddedTrip":false,"AddedStop":false,"LastUpdate":"03:18:05 pm"},{"Pattern":"EB1","Destination":"DOWNTOWN","ExpectedLeaveTime":"4:25pm","ExpectedCountdown":29,"ScheduleStatus":"*","CancelledTrip":false,"CancelledStop":false,"AddedTrip":false,"AddedStop":false,"LastUpdate":"03:24:10 pm"}]}]