[{"RouteNo":"004","RouteName":"POWELL\/DOWNTOWN\/UBC","Direction":"EAST","RouteMap":{"Href":"http:\/\/nb.translink.ca\/geodata\/004.kmz"},"Schedules":[{"Pattern":"EB1","Destination":"POWELL","ExpectedLeaveTime":"6:32pm 2017-08-21","ExpectedCountdown":16,"ScheduleStatus":" ","CancelledTrip":false,"CancelledStop":false,"AddedTrip":false,"AddedStop":false,"LastUpdate":"05:19:07 pm"},{"Pattern":"EB1","Destination":"POWELL","ExpectedLeaveTime":"6:52pm 2017-08-21","ExpectedCountdown":36,"ScheduleStatus":"*","CancelledTrip":false,"CancelledStop":false,"AddedTrip":false,"AddedStop":false,"LastUpdate":"05:39:03 pm"},{"Pattern":"EB1","Destination":"POWELL","ExpectedLeaveTime":"7:12pm 2017-08-21","ExpectedCountdown":56,"ScheduleStatus":" ","CancelledTrip":false,"CancelledStop":false,"AddedTrip":false,"AddedStop":false,"LastUpdate":"05:59:07 pm"},{"Pattern":"EB1","Destination":"POWELL","ExpectedLeaveTime":"7:33pm 2017-08-21","ExpectedCountdown":77,"ScheduleStatus":"*","CancelledTrip":false,"CancelledStop":false,"AddedTrip":false,"AddedStop":false,"LastUpdate":"09:00:05 pm"},{"Pattern":"EBEV4","Destination":"DOWNTOWN","ExpectedLeaveTime":"7:55pm 2017-08-21","ExpectedCountdown":99,"ScheduleStatus":"*","CancelledTrip":false,"CancelledStop":false,"AddedTrip":false,"AddedStop":false,"LastUpdate":"09:00:05 pm"},{"Pattern":"EBEV4","Destination":"DOWNTOWN","ExpectedLeaveTime":"8:15pm 2017-08-21","ExpectedCountdown":119,"ScheduleStatus":"*","CancelledTrip":false,"CancelledStop":false,"AddedTrip":false,"AddedStop":false,"LastUpdate":"09:00:05 pm"}]},{"RouteNo":"007","RouteName":"NANAIMO STN\/DUNBAR             ","Direction":"EAST","RouteMap":{"Href":"http:\/\/nb.translink.ca\/geodata\/007.kmz"},"Schedules":[{"Pattern":"EB1","Destination":"NANAIMO STN","ExpectedLeaveTime":"6:22pm 2017-08-21","ExpectedCountdown":6,"ScheduleStatus":" ","CancelledTrip":false,"CancelledStop":false,"AddedTrip":false,"AddedStop":false,"LastUpdate":"05:08:04 pm"},{"Pattern":"EB1","Destination":"NANAIMO STN","ExpectedLeaveTime":"6:42pm 2017-08-21","ExpectedCountdown":26,"ScheduleStatus":"*","CancelledTrip":false,"CancelledStop":false,"AddedTrip":false,"AddedStop":false,"LastUpdate":"05:28:04 pm"},{"Pattern":"EB1","Destination":"NANAIMO STN","ExpectedLeaveTime":"7:02pm 2017-08-21","ExpectedCountdown":46,"ScheduleStatus":" ","CancelledTrip":false,"CancelledStop":false,"AddedTrip":false,"AddedStop":false,"LastUpdate":"05:49:02 pm"},{"Pattern":"EB1","Destination":"NANAIMO STN","ExpectedLeaveTime":"7:23pm 2017-08-21","ExpectedCountdown":67,"ScheduleStatus":" ","CancelledTrip":false,"CancelledStop":false,"AddedTrip":false,"AddedStop":false,"LastUpdate":"06:11:02 pm"},{"Pattern":"EB1","Destination":"NANAIMO STN","ExpectedLeaveTime":"7:43pm 2017-08-21","ExpectedCountdown":87,"ScheduleStatus":"*","CancelledTrip":false,"CancelledStop":false,"AddedTrip":false,"AddedStop":false,"LastUpdate":"09:00:05 pm"},{"Pattern":"EB1","Destination":"NANAIMO STN","ExpectedLeaveTime":"8:05pm 2017-08-21","ExpectedCountdown":109,"ScheduleStatus":"*","CancelledTrip":false,"CancelledStop":false,"AddedTrip":false,"AddedStop":false,"LastUpdate":"09:00:05 pm"}]},{"RouteNo":"044","RouteName":"UBC\/DOWNTOWN                    ","Direction":"EAST","RouteMap":{"Href":"http:\/\/nb.translink.ca\/geodata\/044.kmz"},"Schedules":[{"Pattern":"EB1","Destination":"DOWNTOWN","ExpectedLeaveTime":"6:23pm 2017-08-21","ExpectedCountdown":7,"ScheduleStatus":"-","CancelledTrip":false,"CancelledStop":false,"AddedTrip":false,"AddedStop":false,"LastUpdate":"04:58:06 pm"},{"Pattern":"EB1","Destination":"DOWNTOWN","ExpectedLeaveTime":"6:39pm 2017-08-21","ExpectedCountdown":23,"ScheduleStatus":"-","CancelledTrip":false,"CancelledStop":false,"AddedTrip":false,"AddedStop":false,"LastUpdate":"05:13:00 pm"},{"Pattern":"EB1","Destination":"DOWNTOWN","ExpectedLeaveTime":"6:48pm 2017-08-21","ExpectedCountdown":32,"ScheduleStatus":"-","CancelledTrip":false,"CancelledStop":false,"AddedTrip":false,"AddedStop":false,"LastUpdate":"05:28:10 pm"},{"Pattern":"EB1","Destination":"DOWNTOWN","ExpectedLeaveTime":"6:58pm 2017-08-21","ExpectedCountdown":42,"ScheduleStatus":"*","CancelledTrip":false,"CancelledStop":false,"AddedTrip":false,"AddedStop":false,"LastUpdate":"05:43:06 pm"},{"Pattern":"EB1","Destination":"DOWNTOWN","ExpectedLeaveTime":"7:13pm 2017-08-21","ExpectedCountdown":57,"ScheduleStatus":" ","CancelledTrip":false,"CancelledStop":false,"AddedTrip":false,"AddedStop":false,"LastUpdate":"05:58:01 pm"},{"Pattern":"EB1","Destination":"DOWNTOWN","ExpectedLeaveTime":"7:33pm 2017-08-21","ExpectedCountdown":77,"ScheduleStatus":"*","CancelledTrip":false,"CancelledStop":false,"AddedTrip":false,"AddedStop":false,"LastUpdate":"09:00:05 pm"}]},{"RouteNo":"084","RouteName":"UBC\/VCC STATION","Direction":"EAST","RouteMap":{"Href":"http:\/\/nb.translink.ca\/geodata\/084.kmz"},"Schedules":[{"Pattern":"EB1","Destination":"VCC-CLARK STN","ExpectedLeaveTime":"6:24pm 2017-08-21","ExpectedCountdown":8,"ScheduleStatus":" ","CancelledTrip":false,"CancelledStop":false,"AddedTrip":false,"AddedStop":false,"LastUpdate":"05:13:01 pm"},{"Pattern":"EB1","Destination":"VCC-CLARK STN","ExpectedLeaveTime":"6:39pm 2017-08-21","ExpectedCountdown":23,"ScheduleStatus":"*","CancelledTrip":false,"CancelledStop":false,"AddedTrip":false,"AddedStop":false,"LastUpdate":"05:28:03 pm"},{"Pattern":"EB1","Destination":"VCC-CLARK STN","ExpectedLeaveTime":"6:54pm 2017-08-21","ExpectedCountdown":38,"ScheduleStatus":"*","CancelledTrip":false,"CancelledStop":false,"AddedTrip":false,"AddedStop":false,"LastUpdate":"05:43:10 pm"},{"Pattern":"EB1","Destination":"VCC-CLARK STN","ExpectedLeaveTime":"7:09pm 2017-08-21","ExpectedCountdown":53,"ScheduleStatus":" ","CancelledTrip":false,"CancelledStop":false,"AddedTrip":false,"AddedStop":false,"LastUpdate":"05:58:01 pm"},{"Pattern":"EB1","Destination":"VCC-CLARK STN","ExpectedLeaveTime":"7:25pm 2017-08-21","ExpectedCountdown":69,"ScheduleStatus":" ","CancelledTrip":false,"CancelledStop":false,"AddedTrip":false,"AddedStop":false,"LastUpdate":"06:14:06 pm"},{"Pattern":"EB1","Destination":"VCC-CLARK STN","ExpectedLeaveTime":"7:40pm 2017-08-21","ExpectedCountdown":84,"ScheduleStatus":"*","CancelledTrip":false,"CancelledStop":false,"AddedTrip":false,"AddedStop":false,"LastUpdate":"09:00:05 pm"}]}]