[{"RouteNo":"250","RouteName":"HORSESHOE BAY\/DUNDARAVE\/VANCOUVER","Direction":"EAST","RouteMap":{"Href":"http:\/\/nb.translink.ca\/geodata\/250.kmz"},"Schedules":[{"Pattern":"EB1","Destination":"VANCOUVER","ExpectedLeaveTime":"5:18pm 2017-08-21","ExpectedCountdown":9,"ScheduleStatus":" ","CancelledTrip":false,"CancelledStop":false,"AddedTrip":false,"AddedStop":false,"LastUpdate":"04:03:14 pm"},{"Pattern":"EB1","Destination":"VANCOUVER","ExpectedLeaveTime":"5:48pm 2017-08-21","ExpectedCountdown":39,"ScheduleStatus":"*","CancelledTrip":false,"CancelledStop":false,"AddedTrip":false,"AddedStop":false,"LastUpdate":"04:33:07 pm"},{"Pattern":"EB1","Destination":"VANCOUVER","ExpectedLeaveTime":"6:18pm 2017-08-21","ExpectedCountdown":69,"ScheduleStatus":" ","CancelledTrip":false,"CancelledStop":false,"AddedTrip":false,"AddedStop":false,"LastUpdate":"05:03:06 pm"},{"Pattern":"EB1","Destination":"VANCOUVER","ExpectedLeaveTime":"6:48pm 2017-08-21","ExpectedCountdown":99,"ScheduleStatus":"*","CancelledTrip":false,"CancelledStop":false,"AddedTrip":false,"AddedStop":false,"LastUpdate":"09:00:05 pm"}]},{"RouteNo":"253","RouteName":"CAULFEILD\/VANCOUVER\/PARK ROYAL","Direction":"EAST","RouteMap":{"Href":"http:\/\/nb.translink.ca\/geodata\/253.kmz"},"Schedules":[{"Pattern":"EB2","Destination":"PARK ROYAL - ONLY","ExpectedLeaveTime":"5:38pm 2017-08-21","ExpectedCountdown":29,"ScheduleStatus":"-","CancelledTrip":false,"CancelledStop":false,"AddedTrip":false,"AddedStop":false,"LastUpdate":"04:28:04 pm"},{"Pattern":"EB1","Destination":"VANCOUVER","ExpectedLeaveTime":"6:07pm 2017-08-21","ExpectedCountdown":58,"ScheduleStatus":"-","CancelledTrip":false,"CancelledStop":false,"AddedTrip":false,"AddedStop":false,"LastUpdate":"05:00:11 pm"},{"Pattern":"EB1","Destination":"VANCOUVER","ExpectedLeaveTime":"6:35pm 2017-08-21","ExpectedCountdown":86,"ScheduleStatus":"*","CancelledTrip":false,"CancelledStop":false,"AddedTrip":false,"AddedStop":false,"LastUpdate":"09:00:05 pm"},{"Pattern":"EB1","Destination":"VANCOUVER","ExpectedLeaveTime":"7:05pm 2017-08-21","ExpectedCountdown":116,"ScheduleStatus":"*","CancelledTrip":false,"CancelledStop":false,"AddedTrip":false,"AddedStop":false,"LastUpdate":"09:00:05 pm"}]}]